persistance_queue/__init__.py
persistance_queue/app.py
persistance_queue/consumer.py
persistance_queue/manager.py
persistance_queue/ops.py
persistance_queue/persistent_q.py
persistance_queue/persistent_q_interface.py
persistance_queue/persistent_queue.db
persistance_queue/producer.py
persistance_queue-0.1.0.dist-info/METADATA
persistance_queue-0.1.0.dist-info/WHEEL
persistance_queue-0.1.0.dist-info/RECORD
