Metadata-Version: 2.1
Name: persistance-queue
Version: 0.1.0
Summary: 
Author: syash-acog
Author-email: syash@aganitha.ai
Requires-Python: >=3.11,<4.0
Classifier: Programming Language :: Python :: 3
Classifier: Programming Language :: Python :: 3.11
Classifier: Programming Language :: Python :: 3.12
Classifier: Programming Language :: Python :: 3.13
Requires-Dist: pysqlite3 (>=0.4.6,<0.5.0)
Requires-Dist: streamlit (>=1.12.0,<2.0.0)
Requires-Dist: typer (>=0.15.1,<0.16.0)
